{
"A/WER": "aware",
"AEU/TKPWEPBT": "agent",
"AL/WAEUS": "always",
"AO*ULT": "util",
"AOU/PWUPBT": "ubuntu",
"ART/TP-BGT/REU": "artifactory",
"AU/T*": "auth",
"E/PHAEUL": "email",
"E/THO": "etho",
"EUPBS/TAUL": "install",
"EUPBS/TED": "instead",
"EUPS/TAL": "install",
"HR*EUFT": "list",
"HR*EULT": "little",
"HR*UFRPB": "lunch",
"HROFT": "lost",
"KA/PHEL": "camel",
"KAEFP": "cache",
"KHR*EU": "cli",
"KROPB": "cron",
"OBG": "ok",
"OE": "oh",
"OR/SKWREUPB": "origin",
"P*EPL": "people",
"PA/PWHRO": "Pablo",
"PEPL": "pem",
"PHRUG/EUPB": "plugin",
"PRO/KPEU": "proxy",
"PRO/KPEUS": "proxies",
"PROBGS/AOE": "proxy",
"PROBGS/EU": "proxy",
"PW*EU/TPHREU": "binary",
"PWAEU/SEUBG": "basic",
"PWAOUPBT": "ubuntu",
"PWR-B": "brb",
"S*EUS": "sys",
"SEUR/KWEUT": "circuit",
"SHA": "sha",
"SR*ERT": "vert",
"SRARBL": "variable",
"SREPB": "env",
"STUS": "status",
"T*EPL/PHRAEUT": "template",
"T*EPL/PHRAEUTS": "templates",
"T*PL": "tmp",
"T-FT": "tst",
"TKE/KRAEURT": "decorator",
"TKEB/KWRAPB": "debian",
"TKEPBT/TPEU": "identify",
"TKEUR": "dir",
"TKPW/PHAEUL": "gmail",
"TKPWHR-L": "glol",
"TO*LG": "toggle",
"TPH-PL": "npm",
"TPHR*UBGS": "linux",
"UP/TKAEUTD": "updated",
"URL": "url",
"W-L": "will",
"WO/REUS": "worries",
"WOD": "word",
"WOR/REUS": "worries"
}